{
  "display": {
    "icon": {
      "id": "player_head",
      "components": {
        "profile": {
          "properties": [
            {
              "name": "textures",
              "value": "eyJ0ZXh0dXJlcyI6eyJTS0lOIjp7InVybCI6Imh0dHA6Ly90ZXh0dXJlcy5taW5lY3JhZnQubmV0L3RleHR1cmUvODg0YjYzZDg0OGRjYmNmMDYxZTY0MmY2OTdiNDZkNTk5YTk0MmUzNmU3ODUzNDdlZmVjOTUzNGNjNzZkOGE2NiJ9fX0="
            }
          ]
        }
      }
    },
    "title": "水属性 [Lv.4]",
    "description": [
      {
        "text": ""
      }
    ],
    "show_toast": true,
    "announce_to_chat": false,
    "hidden": true
  },
  "parent": "saharass:display/skill/water/3",
  "criteria": {
    "requirement": {
      "trigger": "impossible"
    }
  }
}